LICENSE
MANIFEST.in
README.md
pyproject.toml
setup.py
djangogql/__init__.py
djangogql/context.py
djangogql/decorators.py
djangogql/exceptions.py
djangogql/permissions.py
djangogql/settings.py
djangogql/views.py
djangogql/account/__init__.py
djangogql/account/mixins.py
djangogql/core/__init__.py
djangogql/core/connection.py
djangogql/core/context.py
djangogql/core/dataloaders.py
djangogql/core/enums.py
djangogql/core/fields.py
djangogql/core/filters.py
djangogql/core/mutations.py
djangogql/core/validators.py
djangogql/core/types/__init__.py
djangogql/core/types/base.py
djangogql/core/types/common.py
djangogql/core/types/converter.py
djangogql/core/types/filter_input.py
djangogql/core/types/model.py
djangogql/core/types/registry.py
djangogql/core/types/sort_input.py
djangogql/core/types/upload.py
djangogql/db/__init__.py
djangogql/db/utils.py
djangogql/templates/graphql/playground.html
djangogql/utils/__init__.py
djangogql/utils/fields.py
djangogql/utils/files.py
djangogql/utils/filters.py
djangogql/utils/sorting.py
python_djangogql.egg-info/PKG-INFO
python_djangogql.egg-info/SOURCES.txt
python_djangogql.egg-info/dependency_links.txt
python_djangogql.egg-info/not-zip-safe
python_djangogql.egg-info/requires.txt
python_djangogql.egg-info/top_level.txt